cdktf_tf_module_stack/__init__.py
cdktf_tf_module_stack/py.typed
cdktf_tf_module_stack/_jsii/__init__.py
cdktf_tf_module_stack/_jsii/tf-module-stack@7.0.24.jsii.tgz
cdktf_tf_module_stack-7.0.24.dist-info/LICENSE
cdktf_tf_module_stack-7.0.24.dist-info/METADATA
cdktf_tf_module_stack-7.0.24.dist-info/WHEEL
cdktf_tf_module_stack-7.0.24.dist-info/top_level.txt
cdktf_tf_module_stack-7.0.24.dist-info/RECORD
