Metadata-Version: 2.1
Name: cdktf-tf-module-stack
Version: 7.0.24
Summary: A drop-in replacement for cdktf.TerraformStack that lets you define Terraform modules as constructs
Home-page: https://github.com/cdktf/cdktf-tf-module-stack.git
Author: HashiCorp
License: MPL-2.0
Project-URL: Source, https://github.com/cdktf/cdktf-tf-module-stack.git
Classifier: Intended Audience :: Developers
Classifier: Operating System :: OS Independent
Classifier: Programming Language :: JavaScript
Classifier: Programming Language :: Python :: 3 :: Only
Classifier: Programming Language :: Python :: 3.9
Classifier: Programming Language :: Python :: 3.10
Classifier: Programming Language :: Python :: 3.11
Classifier: Typing :: Typed
Classifier: Development Status :: 5 - Production/Stable
Classifier: License :: OSI Approved
Requires-Python: ~=3.9
License-File: LICENSE
Requires-Dist: cdktf >=0.21.0
Requires-Dist: constructs <11.0.0,>=10.4.2
Requires-Dist: jsii <2.0.0,>=1.119.0
Requires-Dist: publication >=0.0.3
Requires-Dist: typeguard <4.3.0,>=2.13.3
